prolint2/__init__.py
prolint2/_version.py
prolint2/config.ini
prolint2/sampledata.py
prolint2/computers/__init__.py
prolint2/computers/base.py
prolint2/computers/contacts.py
prolint2/computers/distances.py
prolint2/computers/payload.py
prolint2/config/__init__.py
prolint2/config/units.py
prolint2/core/__init__.py
prolint2/core/base.py
prolint2/core/contact_provider.py
prolint2/core/groups.py
prolint2/core/typing.py
prolint2/core/universe.py
prolint2/metrics/__init__.py
prolint2/metrics/aprox_contacts.py
prolint2/metrics/base.py
prolint2/metrics/converters.py
prolint2/metrics/exact_contacts.py
prolint2/metrics/fitters.py
prolint2/metrics/formatters.py
prolint2/metrics/metrics.py
prolint2/metrics/registries.py
prolint2/metrics/restime.py
prolint2/metrics/utils.py
prolint2/plotting/__init__.py
prolint2/plotting/multiples.py
prolint2/plotting/plotting.py
prolint2/plotting/projection.py
prolint2/plotting/utils.py
prolint2/server/__init__.py
prolint2/server/chord_utils.py
prolint2/server/index.html
prolint2/server/server.py
prolint2/server/utils.py
prolint2/server/static/css/main.css
prolint2/server/static/css/pdbe-molstar-3.1.0_vendor.css
prolint2/server/static/images/logo.png
prolint2/server/static/js/app.js
prolint2/server/static/js/ganttApp.js
prolint2/server/static/js/heatmapApp.js
prolint2/server/static/js/mol.js
prolint2/server/static/js/network.js
prolint2/server/static/js/pdbe-molstar-plugin-3.1.0_vendor.js
prolint2/server/static/js/pie.js
prolint2/server/static/js/radialApp.js
prolint2/server/static/js/table.js
prolint2/server/static/js/timeseries.js
prolint2/server/static/js/utils.js
prolint2/tests/__init__.py
prolint2/utils/__init__.py
prolint2/utils/utils.py
prolint2-0.0.20.data/scripts/prolint2
prolint2-0.0.20.dist-info/licenses/LICENSE
prolint2-0.0.20.dist-info/METADATA
prolint2-0.0.20.dist-info/WHEEL
prolint2-0.0.20.dist-info/top_level.txt
prolint2-0.0.20.dist-info/RECORD
