Metadata-Version: 2.4
Name: prolint2
Version: 0.0.20
Summary: ProLint2: Lipid-Protein Interaction Analysis.
Home-page: https://github.com/ProLint/prolint2
Author: Daniel P. Ramirez & Besian I. Sejdiu
Author-email: daniel.ramirezecheme@ucalgary.ca
License: MIT
Platform: Linux
Platform: Mac OS-X
Platform: Windows
Requires-Python: >=3.10
License-File: LICENSE
Requires-Dist: pandas
Requires-Dist: mdanalysis
Requires-Dist: bottle
Requires-Dist: jsonargparse[signatures]
Requires-Dist: requests
Requires-Dist: networkx
Requires-Dist: logomaker
Requires-Dist: seaborn
Dynamic: author
Dynamic: author-email
Dynamic: description
Dynamic: description-content-type
Dynamic: home-page
Dynamic: license
Dynamic: license-file
Dynamic: platform
Dynamic: requires-dist
Dynamic: requires-python
Dynamic: summary
